cognita/__init__.py
cognita/factbase.py
cognita/goal_solver.py
cognita/rule_engine.py
cognita_toolkit-1.0.0.dist-info/METADATA
cognita_toolkit-1.0.0.dist-info/WHEEL
cognita_toolkit-1.0.0.dist-info/top_level.txt
cognita_toolkit-1.0.0.dist-info/RECORD
