Metadata-Version: 2.4
Name: cognita-toolkit
Version: 1.0.0
Summary: A symbolic reasoning toolkit for building logic-driven agents and AGI research.
Author: Aditya Kharat
Classifier: Programming Language :: Python :: 3
Classifier: License :: OSI Approved :: MIT License
Classifier: Operating System :: OS Independent
Requires-Python: >=3.7
Dynamic: author
Dynamic: classifier
Dynamic: description
Dynamic: description-content-type
Dynamic: requires-python
Dynamic: summary
